__init__.py
ai_atlas_nexus/__init__.py
ai_atlas_nexus/exceptions.py
ai_atlas_nexus/extension.py
ai_atlas_nexus/library.py
ai_atlas_nexus/metadata_base.py
ai_atlas_nexus/ai_risk_ontology/__init__.py
ai_atlas_nexus/ai_risk_ontology/datamodel/__init__.py
ai_atlas_nexus/ai_risk_ontology/datamodel/ai_risk_ontology.py
ai_atlas_nexus/ai_risk_ontology/schema/ai-risk-ontology.yaml
ai_atlas_nexus/ai_risk_ontology/schema/ai_capability.yaml
ai_atlas_nexus/ai_risk_ontology/schema/ai_csiro_rai.yaml
ai_atlas_nexus/ai_risk_ontology/schema/ai_eval.yaml
ai_atlas_nexus/ai_risk_ontology/schema/ai_intrinsic.yaml
ai_atlas_nexus/ai_risk_ontology/schema/ai_risk.yaml
ai_atlas_nexus/ai_risk_ontology/schema/ai_system.yaml
ai_atlas_nexus/ai_risk_ontology/schema/common.yaml
ai_atlas_nexus/ai_risk_ontology/schema/energy.yaml
ai_atlas_nexus/ai_risk_ontology/schema/eu_ai_act.yaml
ai_atlas_nexus/ai_risk_ontology/schema/semweb_context.yaml
ai_atlas_nexus/ai_risk_ontology/util/__init__.py
ai_atlas_nexus/ai_risk_ontology/util/air_2024_risks2linkml.py
ai_atlas_nexus/ai_risk_ontology/util/credo2linkml.py
ai_atlas_nexus/ai_risk_ontology/util/export_cypher.py
ai_atlas_nexus/ai_risk_ontology/util/export_graph.py
ai_atlas_nexus/ai_risk_ontology/util/export_json_graph.py
ai_atlas_nexus/ai_risk_ontology/util/export_risk_atlas_tex.py
ai_atlas_nexus/ai_risk_ontology/util/json_graph_dumper.py
ai_atlas_nexus/ai_risk_ontology/util/latex_dumper.py
ai_atlas_nexus/ai_risk_ontology/util/mitriskrepo2linkml.py
ai_atlas_nexus/ai_risk_ontology/util/nistUpdateLinkmlWithActions.py
ai_atlas_nexus/ai_risk_ontology/util/nistactions2linkml.py
ai_atlas_nexus/ai_risk_ontology/util/riskatlas2linkml.py
ai_atlas_nexus/ai_risk_ontology/util/lifting/__init__.py
ai_atlas_nexus/ai_risk_ontology/util/lifting/import_entity_mappings.py
ai_atlas_nexus/blocks/prompt_builder.py
ai_atlas_nexus/blocks/prompt_response_schema.py
ai_atlas_nexus/blocks/prompt_templates.py
ai_atlas_nexus/blocks/atlas_explorer/__init__.py
ai_atlas_nexus-1.2.0.dist-info/licenses/LICENSE
ai_atlas_nexus-1.2.0.dist-info/METADATA
ai_atlas_nexus-1.2.0.dist-info/WHEEL
ai_atlas_nexus-1.2.0.dist-info/entry_points.txt
ai_atlas_nexus-1.2.0.dist-info/top_level.txt
ai_atlas_nexus-1.2.0.dist-info/RECORD
