Metadata-Version: 2.4
Name: ai-atlas-nexus
Version: 1.2.0
Summary: AI Atlas Nexus provides tooling to help bring together disparate resources related to governance of foundation models. 
Author-email: AI Atlas Nexus <ai-atlas-nexus@ibm.com>, Elizabeth Daly <elizabeth.daly@ie.ibm.com>, Dhaval Salwala <dhaval.vinodbhai.salwala@ibm.com>, Frank Bagehorn <fba@zurich.ibm.com>, Luis Garces-Erice <lga@zurich.ibm.com>, Sean Rooney <sro@zurich.ibm.com>, Inge Vejsbjerg <ingevejs@ie.ibm.com>
Project-URL: Homepage, https://github.com/IBM/ai-atlas-nexus
Project-URL: Documentation, https://ibm.github.io/ai-atlas-nexus/
Project-URL: Changelog, https://github.com/IBM/ai-atlas-nexus/blob/main/CHANGELOG.md
Project-URL: Issues, https://github.com/IBM/ai-atlas-nexus/issues
Keywords: ai risks,ai safety,ai governance,risk taxonomies,risk identification,risk detection,ai task identification,ai risk management,ai risk questionnaire,ai systems modelling,knowledge graph,chain of thought
Classifier: Intended Audience :: Developers
Classifier: Intended Audience :: Science/Research
Classifier: Programming Language :: Python :: 3
Classifier: Topic :: Software Development
Classifier: Topic :: Scientific/Engineering :: Artificial Intelligence
Classifier: License :: OSI Approved :: Apache Software License
Classifier: Operating System :: MacOS :: MacOS X
Classifier: Operating System :: POSIX :: Linux
Classifier: Operating System :: Microsoft :: Windows
Requires-Python: <3.12.5,>=3.11
License-File: LICENSE
Requires-Dist: linkml
Requires-Dist: linkml_runtime
Requires-Dist: pydantic
Requires-Dist: requests
Requires-Dist: rich
Requires-Dist: sssom
Requires-Dist: txtai
Requires-Dist: tqdm
Requires-Dist: logzero
Requires-Dist: python-dotenv
Requires-Dist: datasets
Requires-Dist: openai>=1.0
Requires-Dist: txtai
Requires-Dist: jsonschema
Requires-Dist: isort
Requires-Dist: pre-commit
Requires-Dist: typer
Requires-Dist: inflect
Provides-Extra: wml
Requires-Dist: ibm-watsonx-ai; extra == "wml"
Provides-Extra: ollama
Requires-Dist: ollama; extra == "ollama"
Provides-Extra: vllm
Requires-Dist: vllm; extra == "vllm"
Requires-Dist: xgrammar; extra == "vllm"
Provides-Extra: docs
Requires-Dist: mkdocs-material; extra == "docs"
Requires-Dist: mkdocs-jupyter; extra == "docs"
Requires-Dist: mkdocs-click; extra == "docs"
Requires-Dist: mkdocstrings[python]; extra == "docs"
Requires-Dist: griffe_inherited_docstrings; extra == "docs"
Requires-Dist: griffe-pydantic; extra == "docs"
Requires-Dist: mkdocs-awesome-nav; extra == "docs"
Dynamic: license-file
